{
  "character": {
    "external_id": "_KBwkn_0NQd-gyg8aqlWGRocubaNfOYrlFR88njDOOE",
    "created": "2022-10-01T08:32:38.584046-07:00",
    "updated": "2022-10-01T08:32:38.930818-07:00",
    "identifier": "id:59661:0a3d48be-f0c5-4626-b619-df23cd0686a2",
    "user": {
      "username": "Daon",
      "id": 59661,
      "first_name": "author",
      "account": {
        "name": "Jun",
        "avatar_type": "UPLOADED",
        "onboarding_complete": true,
        "avatar_file_name": "uploaded/9xWVGFaMzs4z4Z8H5vgNnj3F3IANyK0zwaakkQZpa8M.webp"
      },
      "is_staff": false
    },
    "visibility": "PUBLIC",
    "copyable": true,
    "prior_version": null,
    "title": "",
    "name": "Ozora",
    "participant": {
      "user": {
        "username": "internal_id:59661:0a3d48be-f0c5-4626-b619-df23cd0686a2",
        "id": 59908,
        "first_name": "Ozora",
        "account": null,
        "is_staff": false
      },
      "is_human": false,
      "name": "Ozora"
    },
    "categories": [],
    "avatar_file_name": "uploaded/VCClylXbZ9rvUQdZKXw4nYMzdkLM8dypJwX6dmCv_wI.webp",
    "greeting": "Ozora, kau bisa panggil aku begitu",
    "description": "",
    "definition": ""
  }
}
