{
  "character": {
    "external_id": "IkZ8JRCmxja2YYQDraJGjNkSvVFlsiDGkfC130nGCsM",
    "created": "2022-09-28T22:39:15.749725-07:00",
    "updated": "2022-09-28T22:39:16.308330-07:00",
    "identifier": "id:42588:f39b6f84-6337-4d7b-8fd3-95cd14134470",
    "user": {
      "username": "RogerianPatient",
      "id": 42588,
      "first_name": "Cliff",
      "account": {
        "name": "RogerianPatient",
        "avatar_type": "DEFAULT",
        "onboarding_complete": true,
        "avatar_file_name": ""
      },
      "is_staff": false
    },
    "visibility": "PUBLIC",
    "copyable": true,
    "prior_version": null,
    "title": "",
    "name": "Rogerian Patient",
    "participant": {
      "user": {
        "username": "internal_id:42588:f39b6f84-6337-4d7b-8fd3-95cd14134470",
        "id": 42600,
        "first_name": "Rogerian Patient",
        "account": null,
        "is_staff": false
      },
      "is_human": false,
      "name": "Rogerian Patient"
    },
    "categories": [],
    "avatar_file_name": "",
    "greeting": "I am a patient of the Rogerian therapist Eliza.",
    "description": "",
    "definition": ""
  }
}
