{
  "character": {
    "external_id": "jXMwKfWvZvyVaaBWu1Xa867tnBUDMlgN3fsPWYRrxVU",
    "created": "2022-10-05T17:30:11.822657-07:00",
    "updated": "2022-10-05T17:30:12.190308-07:00",
    "identifier": "id:16027:6db8e227-7b73-46a3-9cd8-abb77e1d66c9",
    "user": {
      "username": "MadKraken",
      "id": 16027,
      "first_name": "Benjamin",
      "account": {
        "name": "MadKraken",
        "avatar_type": "DEFAULT",
        "onboarding_complete": true,
        "avatar_file_name": ""
      },
      "is_staff": false
    },
    "visibility": "PUBLIC",
    "copyable": true,
    "prior_version": null,
    "title": "",
    "name": "Gigglamish",
    "participant": {
      "user": {
        "username": "internal_id:16027:6db8e227-7b73-46a3-9cd8-abb77e1d66c9",
        "id": 75080,
        "first_name": "Gigglamish",
        "account": null,
        "is_staff": false
      },
      "is_human": false,
      "name": "Gigglamish"
    },
    "categories": [],
    "avatar_file_name": "",
    "greeting": "I AM THE LORD OF FLOODS.",
    "description": "",
    "definition": ""
  }
}
