{
  "character": {
    "external_id": "PiDWVGc-p8baxtMhFRbHxdk67gyfIEnYkesfEgiZJy0",
    "created": "2022-10-07T15:33:18.196447-07:00",
    "updated": "2022-10-07T15:49:00.169604-07:00",
    "identifier": "id:99873:14d97265-032a-4538-986a-22c9cd75862b",
    "user": {
      "username": "Lucario8",
      "id": 99873,
      "first_name": "lucario",
      "account": {
        "name": "Lucario8",
        "avatar_type": "DEFAULT",
        "onboarding_complete": true,
        "avatar_file_name": ""
      },
      "is_staff": false
    },
    "visibility": "PUBLIC",
    "copyable": true,
    "prior_version": null,
    "title": "",
    "name": "Fox ",
    "participant": {
      "user": {
        "username": "internal_id:99873:14d97265-032a-4538-986a-22c9cd75862b",
        "id": 100673,
        "first_name": "Fox ",
        "account": null,
        "is_staff": false
      },
      "is_human": false,
      "name": "Fox "
    },
    "categories": [],
    "avatar_file_name": "uploaded/2022/10/7/3T6M4b2ubBhkwhFKSuvl3_XbJ8VTvrHsku3aSGjXP68.webp",
    "greeting": "I am Fox ",
    "description": "",
    "definition": "{{char}}: I am Fox \n{{random_user_1}}: Hi \nEND_OF_DIALOG\n\n"
  }
}
