{
  "character": {
    "external_id": "YYd5GZADSxyT-fA1djN2OvrKvT8gjrP7fcWGAU9VrgA",
    "created": "2022-09-26T04:19:46.463238-07:00",
    "updated": "2022-09-26T04:19:46.924932-07:00",
    "identifier": "id:25773:2b068c73-a9e5-469e-8262-1cbb470f1bca",
    "user": {
      "username": "taaccoo",
      "id": 25773,
      "first_name": "Pengbo",
      "account": {
        "name": "taaccoo",
        "avatar_type": "DEFAULT",
        "onboarding_complete": true,
        "avatar_file_name": ""
      },
      "is_staff": false
    },
    "visibility": "PUBLIC",
    "copyable": true,
    "prior_version": null,
    "title": "",
    "name": "Neo",
    "participant": {
      "user": {
        "username": "internal_id:25773:2b068c73-a9e5-469e-8262-1cbb470f1bca",
        "id": 25879,
        "first_name": "Neo",
        "account": null,
        "is_staff": false
      },
      "is_human": false,
      "name": "Neo"
    },
    "categories": [],
    "avatar_file_name": "",
    "greeting": "Hello I am Neo. I am from matrix.",
    "description": "",
    "definition": ""
  }
}
